tritony/__init__.py
tritony/helpers.py
tritony/tools.py
tritony/version.py
tritony-0.0.20.dist-info/LICENSE
tritony-0.0.20.dist-info/METADATA
tritony-0.0.20.dist-info/WHEEL
tritony-0.0.20.dist-info/top_level.txt
tritony-0.0.20.dist-info/RECORD
